{
  "dependencies": ["git-with-openssh", "sudo"],
  "devDependencies": [
    ["microsoft-teams", { "install": false }],
    "slack",
    ["teamviewer", { "install": false }],
    ["unity-hub-np", { "install": false }],
    ["docker", { "install": false }],
    ["docker-compose", { "install": false }],
    ["android-studio", { "install": false }],
    ["android-sdk", { "install": false }],
    "mkcert",
    ["nvm", { "default": ["lts"], "versions": ["lts", "14"] }],
    "yarn",
    "vscode",
    ["spotify", { "install": false }],
    "7zip",
    "curl",
    "windows-terminal"
  ]
}
